[
	{
		"id": 1,
		"header": "Combine like variables",
		"title": "CombineLikeVariables",
		"description": "Amy understands well that if two terms have the same variables, she can add or subtract their coefficients to get a single term.",
		"examples": [
			{
				"id": 1,
				"eqns": [
					{ "id": 1, "eqn": "3xy + 4xy + 5" },
					{ "id": 2, "eqn": "\\Downarrow" },
					{
						"id": 3,
						"eqn": "\\enclose{circle}[mathcolor=\"green\"]{7xy} + 5"
					}
				]
			},
			{
				"id": 2,
				"eqns": [
					{ "id": 1, "eqn": "8x - 2x - 3" },
					{ "id": 2, "eqn": "\\Downarrow" },
					{
						"id": 3,
						"eqn": "\\enclose{circle}[mathcolor=\"green\"]{6x} - 3"
					}
				]
			}
		]
	},
	{
		"id": 2,
		"header": "Combine unlike terms",
		"title": "CombineUnlikeTerms",
		"description": "Amy could have mistakenly combined terms with different variables.",
		"examples": [
			{
				"id": 1,
				"eqns": [
					{ "id": 1, "eqn": "2 + 3x" },
					{ "id": 2, "eqn": "\\Downarrow" },
					{
						"id": 3,
						"eqn": "\\enclose{circle}[mathcolor=\"red\"]{5x}"
					}
				]
			},
			{
				"id": 2,
				"eqns": [
					{ "id": 1, "eqn": "5 - 2x" },
					{ "id": 2, "eqn": "\\Downarrow" },
					{
						"id": 3,
						"eqn": "\\enclose{circle}[mathcolor=\"red\"]{3}"
					}
				]
			}
		]
	},
	{
		"id": 3,
		"header": "Move Variable to Left Side",
		"title": "MoveVariableLeftSide",
		"description": "Amy sometimes moves variable terms from the right side of an equation to the left. In the future steps, she can then combine them to simplify the equation.",
		"examples": [
			{
				"id": 1,
				"eqns": [
					{ "id": 1, "eqn": "2x = x + 3" },
					{ "id": 2, "eqn": "\\Downarrow" },
					{
						"id": 3,
						"eqn": "2x \\enclose{circle}[mathcolor=\"green\"]{-x} = x + 3 \\enclose{circle}[mathcolor=\"green\"]{-x}"
					}
				]
			},
			{
				"id": 2,
				"eqns": [
					{ "id": 1, "eqn": "-5x=-6x + 2" },
					{ "id": 2, "eqn": "\\Downarrow" },
					{
						"id": 3,
						"eqn": "-5x  \\enclose{circle}[mathcolor=\"green\"]{+6x}=-6x + 2 \\enclose{circle}[mathcolor=\"green\"]{+6x}"
					}
				]
			}
		]
	},
	{
		"id": 4,
		"header": "Cancel opposite terms on opposite sides",
		"title": "CancelOppTermsOppSides",
		"description": "Amy could have mistakenly canceled opposite terms even when they were not on the same side.",
		"examples": [
			{
				"id": 1,
				"eqns": [
					{
						"id": 1,
						"eqn": "\\enclose{circle}[mathcolor=\"red\"]{3x} - 2= 3  \\enclose{circle}[mathcolor=\"red\"]{-3x}"
					},
					{ "id": 2, "eqn": "\\Downarrow" },
					{
						"id": 3,
						"eqn": "-2 = 3"
					}
				]
			},
			{
				"id": 2,
				"eqns": [
					{
						"id": 1,
						"eqn": "4x + \\enclose{circle}[mathcolor=\"red\"]{2} = \\enclose{circle}[mathcolor=\"red\"]{-2}+ 7x + 5"
					},
					{ "id": 2, "eqn": "\\Downarrow" },
					{
						"id": 3,
						"eqn": "4x = 7x + 5"
					}
				]
			}
		]
	}
]
